Metadata-Version: 2.1
Name: testsimpleproject
Version: 0.0.5
Summary: A very basic calculator
Home-page: 
Author: Vismaya Murugan
Author-email: muruganvichunni@gmail.com
License: MIT
Keywords: calculator
Classifier: Development Status :: 5 - Production/Stable
Classifier: Intended Audience :: Education
Classifier: Operating System :: Microsoft :: Windows :: Windows 10
Classifier: License :: OSI Approved :: MIT License
Classifier: Programming Language :: Python :: 3
License-File: LICENSE.txt
